[
  {
    "model_name": "mf",
    "aggregation": "product",
    "k": 5,
    "recall_at_k": 0.0,
    "hr_at_k": 0.8069815195071869,
    "ndcg_at_k": 0.5127068307998565
  },
  {
    "model_name": "mf",
    "aggregation": "harmonic",
    "k": 5,
    "recall_at_k": 0.0,
    "hr_at_k": 0.7946611909650924,
    "ndcg_at_k": 0.49819977306838537
  },
  {
    "model_name": "neumf",
    "aggregation": "product",
    "k": 5,
    "recall_at_k": 0.0,
    "hr_at_k": 0.8316221765913757,
    "ndcg_at_k": 0.5803800027533044
  },
  {
    "model_name": "neumf",
    "aggregation": "harmonic",
    "k": 5,
    "recall_at_k": 0.0,
    "hr_at_k": 0.8316221765913757,
    "ndcg_at_k": 0.5806433133822655
  }
]